yaweather/__init__.py
yaweather/api.py
yaweather/cities.py
yaweather/models/__init__.py
yaweather/models/base.py
yaweather/models/fact.py
yaweather/models/forecast.py
yaweather/models/info.py
yaweather/models/request.py
yaweather/models/response.py
yaweather-1.3.0.dist-info/LICENSE
yaweather-1.3.0.dist-info/METADATA
yaweather-1.3.0.dist-info/WHEEL
yaweather-1.3.0.dist-info/top_level.txt
yaweather-1.3.0.dist-info/RECORD
