Metadata-Version: 2.1
Name: yaweather
Version: 1.3.0
Summary: Yandex Weather API with asyncio support and typings
Author-email: uburuntu <github@rmbk.me>
License: MIT
Project-URL: Homepage, https://github.com/uburuntu/yaweather
Project-URL: Download, https://github.com/uburuntu/yaweather/archive/master.zip
Keywords: yandex,ya,weather,api
Platform: all
Classifier: Development Status :: 5 - Production/Stable
Classifier: Framework :: AsyncIO
Classifier: Intended Audience :: Developers
Classifier: Intended Audience :: System Administrators
Classifier: License :: OSI Approved :: MIT License
Classifier: Programming Language :: Python :: 3
Classifier: Typing :: Typed
License-File: LICENSE
Requires-Dist: aiohttp>=3.6
Requires-Dist: pydantic>=2.5
Requires-Dist: requests>=2.24
Provides-Extra: dev
Requires-Dist: codecov>=2.0; extra == "dev"
Requires-Dist: pytest>=5.4; extra == "dev"
Requires-Dist: pytest-asyncio>=0.12; extra == "dev"
Requires-Dist: pytest-cov>=2.8; extra == "dev"
